mom/__init__.py
mom/__main__.py
mom/cli.py
mom/commands/__init__.py
mom/commands/cover.py
mom/commands/focus.py
mom/commands/nag.py
mom/commands/plan.py
mom/commands/status.py
mom/commands/suggest.py
mom/commands/tidy.py
mom/utils/__init__.py
mom/utils/git.py
mom/utils/style.py
mom_cli-0.1.0.dist-info/licenses/LICENSE
mom_cli-0.1.0.dist-info/METADATA
mom_cli-0.1.0.dist-info/WHEEL
mom_cli-0.1.0.dist-info/entry_points.txt
mom_cli-0.1.0.dist-info/top_level.txt
mom_cli-0.1.0.dist-info/RECORD
