Metadata-Version: 2.4
Name: mom-cli
Version: 0.1.0
Summary: Your code’s mom. She’s watching. And judging.
Author-email: Alex Previato <hi.previalex@icloud.com>
License: MIT
Requires-Python: >=3.8
License-File: LICENSE
Requires-Dist: click>=8.0
Requires-Dist: rich>=13.0
Requires-Dist: python-dateutil>=2.8
Dynamic: license-file
